odoo10_addon_l10n_ch_qr_bill-10.0.1.2.3-py3.6-nspkg.pth
odoo/addons/l10n_ch_qr_bill/README.rst
odoo/addons/l10n_ch_qr_bill/__init__.py
odoo/addons/l10n_ch_qr_bill/__manifest__.py
odoo/addons/l10n_ch_qr_bill/controllers/__init__.py
odoo/addons/l10n_ch_qr_bill/controllers/main.py
odoo/addons/l10n_ch_qr_bill/data/paperformat.xml
odoo/addons/l10n_ch_qr_bill/i18n/de.po
odoo/addons/l10n_ch_qr_bill/i18n/fr.po
odoo/addons/l10n_ch_qr_bill/i18n/it.po
odoo/addons/l10n_ch_qr_bill/i18n/l10n_ch_qr_bill.pot
odoo/addons/l10n_ch_qr_bill/models/__init__.py
odoo/addons/l10n_ch_qr_bill/models/account_invoice.py
odoo/addons/l10n_ch_qr_bill/models/report.py
odoo/addons/l10n_ch_qr_bill/models/res_bank.py
odoo/addons/l10n_ch_qr_bill/report/swissqr_report.xml
odoo/addons/l10n_ch_qr_bill/static/description/icon.png
odoo/addons/l10n_ch_qr_bill/static/src/css/report_swissqr.css
odoo/addons/l10n_ch_qr_bill/static/src/img/CH-Cross_7mm.png
odoo/addons/l10n_ch_qr_bill/tests/__init__.py
odoo/addons/l10n_ch_qr_bill/tests/test_is_qr_iban.py
odoo/addons/l10n_ch_qr_bill/tests/test_swissqr.py
odoo/addons/l10n_ch_qr_bill/views/account_invoice_view.xml
odoo/addons/l10n_ch_qr_bill/views/res_bank.xml
odoo10_addon_l10n_ch_qr_bill-10.0.1.2.3.dist-info/METADATA
odoo10_addon_l10n_ch_qr_bill-10.0.1.2.3.dist-info/WHEEL
odoo10_addon_l10n_ch_qr_bill-10.0.1.2.3.dist-info/namespace_packages.txt
odoo10_addon_l10n_ch_qr_bill-10.0.1.2.3.dist-info/top_level.txt
odoo10_addon_l10n_ch_qr_bill-10.0.1.2.3.dist-info/RECORD
