Metadata-Version: 2.1
Name: odoo10-addon-l10n-ch-qr-bill
Version: 10.0.1.2.3
Summary: Print QR-bill for your invoices [Backport from Odoo l10n_ch]
Home-page: https://github.com/OCA/l10n-switzerland
Author: Camptocamp,Odoo Community Association (OCA)
Author-email: support@odoo-community.org
License: LGPL-3
Platform: UNKNOWN
Classifier: Programming Language :: Python
Classifier: Framework :: Odoo
Classifier: License :: OSI Approved :: GNU Lesser General Public License v3 (LGPLv3)
Requires-Python: ~=2.7
Requires-Dist: odoo (<10.1dev,>=10.0)
